krikos/__init__.py
krikos/data/__init__.py
krikos/data/loader.py
krikos/data/utils.py
krikos/nn/__init__.py
krikos/nn/layer.py
krikos/nn/loss.py
krikos/nn/network.py
krikos/nn/regularization.py
krikos-0.1.dist-info/DESCRIPTION.rst
krikos-0.1.dist-info/METADATA
krikos-0.1.dist-info/RECORD
krikos-0.1.dist-info/WHEEL
krikos-0.1.dist-info/metadata.json
krikos-0.1.dist-info/top_level.txt
